pulumi_cloudngfwaws/__init__.py
pulumi_cloudngfwaws/_inputs.py
pulumi_cloudngfwaws/_utilities.py
pulumi_cloudngfwaws/account.py
pulumi_cloudngfwaws/account_onboarding.py
pulumi_cloudngfwaws/account_onboarding_stack.py
pulumi_cloudngfwaws/certificate.py
pulumi_cloudngfwaws/commit_rulestack.py
pulumi_cloudngfwaws/custom_url_category.py
pulumi_cloudngfwaws/fqdn_list.py
pulumi_cloudngfwaws/get_account.py
pulumi_cloudngfwaws/get_accounts.py
pulumi_cloudngfwaws/get_app_id_version.py
pulumi_cloudngfwaws/get_app_id_versions.py
pulumi_cloudngfwaws/get_certificate.py
pulumi_cloudngfwaws/get_country.py
pulumi_cloudngfwaws/get_custom_url_category.py
pulumi_cloudngfwaws/get_fqdn_list.py
pulumi_cloudngfwaws/get_intelligent_feed.py
pulumi_cloudngfwaws/get_ngfw.py
pulumi_cloudngfwaws/get_ngfw_log_profile.py
pulumi_cloudngfwaws/get_ngfws.py
pulumi_cloudngfwaws/get_predefined_url_categories.py
pulumi_cloudngfwaws/get_predefined_url_category_override.py
pulumi_cloudngfwaws/get_prefix_list.py
pulumi_cloudngfwaws/get_rulestack.py
pulumi_cloudngfwaws/get_security_rule.py
pulumi_cloudngfwaws/get_validate_rulestack.py
pulumi_cloudngfwaws/intelligent_feed.py
pulumi_cloudngfwaws/ngfw.py
pulumi_cloudngfwaws/ngfw_log_profile.py
pulumi_cloudngfwaws/outputs.py
pulumi_cloudngfwaws/predefined_url_category_override.py
pulumi_cloudngfwaws/prefix_list.py
pulumi_cloudngfwaws/provider.py
pulumi_cloudngfwaws/pulumi-plugin.json
pulumi_cloudngfwaws/py.typed
pulumi_cloudngfwaws/rulestack.py
pulumi_cloudngfwaws/security_rule.py
pulumi_cloudngfwaws/config/__init__.py
pulumi_cloudngfwaws/config/__init__.pyi
pulumi_cloudngfwaws/config/vars.py
pulumi_cloudngfwaws-1.0.0.dist-info/METADATA
pulumi_cloudngfwaws-1.0.0.dist-info/WHEEL
pulumi_cloudngfwaws-1.0.0.dist-info/top_level.txt
pulumi_cloudngfwaws-1.0.0.dist-info/RECORD
